django_microsoft_sso/__init__.py
django_microsoft_sso/admin.py
django_microsoft_sso/apps.py
django_microsoft_sso/checks/__init__.py
django_microsoft_sso/checks/warnings.py
django_microsoft_sso/conf.py
django_microsoft_sso/helpers.py
django_microsoft_sso/hooks.py
django_microsoft_sso/main.py
django_microsoft_sso/migrations/0001_initial.py
django_microsoft_sso/migrations/0002_microsoftssouser_user_principal_name.py
django_microsoft_sso/migrations/__init__.py
django_microsoft_sso/models.py
django_microsoft_sso/static/django_microsoft_sso/microsoft_button.css
django_microsoft_sso/templates/microsoft_sso/login.html
django_microsoft_sso/templates/microsoft_sso/login_sso.html
django_microsoft_sso/templatetags/__init__.py
django_microsoft_sso/templatetags/show_form.py
django_microsoft_sso/templatetags/sso_tags.py
django_microsoft_sso/tests/__init__.py
django_microsoft_sso/tests/conftest.py
django_microsoft_sso/tests/test_callables.py
django_microsoft_sso/tests/test_conf.py
django_microsoft_sso/tests/test_microsoft_auth.py
django_microsoft_sso/tests/test_models.py
django_microsoft_sso/tests/test_sites.py
django_microsoft_sso/tests/test_tags.py
django_microsoft_sso/tests/test_user_helper.py
django_microsoft_sso/tests/test_views.py
django_microsoft_sso/urls.py
django_microsoft_sso/utils.py
django_microsoft_sso/views.py
django_microsoft_sso-6.0.2.dist-info/METADATA
django_microsoft_sso-6.0.2.dist-info/WHEEL
django_microsoft_sso-6.0.2.dist-info/licenses/LICENSE
django_microsoft_sso-6.0.2.dist-info/RECORD
